Scripts/Spotify.py
Scripts/__init__.py
my_tests/__init__.py
my_tests/test_runDaily.py
my_tests/test_runHourly.py
J_Spotify_recommendation-0.1.8.dist-info/METADATA
J_Spotify_recommendation-0.1.8.dist-info/WHEEL
J_Spotify_recommendation-0.1.8.dist-info/top_level.txt
J_Spotify_recommendation-0.1.8.dist-info/RECORD
