Metadata-Version: 2.1
Name: J-Spotify-recommendation
Version: 0.1.8
Summary: Create playlist with simple decision tree of your tracks in spotify
Home-page: UNKNOWN
Author: JonnyMurillo
Author-email: jonnymurillo288@gmail.com
License: UNKNOWN
Platform: UNKNOWN
